{
    "etf_id": "00988A",
    "date": "2026-06-23",
    "holdings": [
        {
            "id": "MU US",
            "name": "MICRON TECHNOLOGY INC",
            "share": 116000.0
        },
        {
            "id": "009150 KS",
            "name": "Samsung Electro-Mechanics co(009150 ks)",
            "share": 80000.0
        },
        {
            "id": "285A JP",
            "name": "KIOXIA HOLDINGS CORP",
            "share": 168000.0
        },
        {
            "id": "AMD US",
            "name": "ADVANCED MICRO DEVICES.amd us(超微半導體公司)",
            "share": 185000.0
        },
        {
            "id": "SNDK US",
            "name": "SANDISK CORP",
            "share": 39000.0
        },
        {
            "id": "MRVL US",
            "name": "MARVELL TECHNOLOGY INC",
            "share": 230000.0
        },
        {
            "id": "6981 JP",
            "name": "MURATA MANUFACTURING CO LTD",
            "share": 960000.0
        },
        {
            "id": "BE US",
            "name": "BLOOM ENERGY CORP- A",
            "share": 190220.0
        },
        {
            "id": "2383",
            "name": "台光電",
            "share": 330000.0
        },
        {
            "id": "2454",
            "name": "聯發科",
            "share": 410000.0
        },
        {
            "id": "WDC US",
            "name": "WESTERN DIGITAL CORP",
            "share": 72000.0
        },
        {
            "id": "LITE US",
            "name": "LUMENTUM HOLDINGS INC",
            "share": 62000.0
        },
        {
            "id": "IFX GY",
            "name": "INFINEON TECHNOLOGIES AG",
            "share": 557550.0
        },
        {
            "id": "3037",
            "name": "欣興",
            "share": 1650000.0
        },
        {
            "id": "6976 JP",
            "name": "TAIYO YUDEN CO LTD",
            "share": 380000.0
        },
        {
            "id": "4062 JP",
            "name": "IBIDEN CO LTD",
            "share": 275000.0
        },
        {
            "id": "6997 JP",
            "name": "NIPPON CHEMI-CON CORP",
            "share": 1275100.0
        },
        {
            "id": "6787 JP",
            "name": "MEIKO ELECTRONICS CO LTD",
            "share": 175000.0
        },
        {
            "id": "5706 JP",
            "name": "Mitsui Mining ＆ Smelting Co",
            "share": 130000.0
        },
        {
            "id": "VSH US",
            "name": "VISHAY INTERTECHNOLOGY INC",
            "share": 580429.0
        },
        {
            "id": "ARM US",
            "name": "ARM HOLDINGS PLC",
            "share": 80000.0
        },
        {
            "id": "BESI NA",
            "name": "BE SEMICONDUCTOR INDUSTRIES",
            "share": 90000.0
        },
        {
            "id": "6920 JP",
            "name": "LASERTEC CORP",
            "share": 87500.0
        },
        {
            "id": "2330",
            "name": "台積電",
            "share": 400000.0
        },
        {
            "id": "8035 JP",
            "name": "TOKYO ELECTRON LTD",
            "share": 62000.0
        },
        {
            "id": "STM US",
            "name": "STMICROELECTRONICS NV-NY SHS",
            "share": 375000.0
        },
        {
            "id": "5274",
            "name": "信驊",
            "share": 46000.0
        },
        {
            "id": "AIXA GY",
            "name": "AIXTRON SE",
            "share": 380000.0
        },
        {
            "id": "CRDO US",
            "name": "CREDO TECHNOLOGY GROUP HOLDI",
            "share": 97000.0
        },
        {
            "id": "6515",
            "name": "穎崴",
            "share": 88000.0
        },
        {
            "id": "2308",
            "name": "台達電",
            "share": 350000.0
        },
        {
            "id": "3436 JP",
            "name": "SUMCO CORP",
            "share": 875400.0
        },
        {
            "id": "6223",
            "name": "旺矽",
            "share": 115000.0
        },
        {
            "id": "7826 JP",
            "name": "FURUYA METAL CO LTD",
            "share": 374300.0
        },
        {
            "id": "COHR US",
            "name": "COHERENT INC",
            "share": 55000.0
        },
        {
            "id": "3711",
            "name": "日月光投控",
            "share": 1100000.0
        },
        {
            "id": "CRWD US",
            "name": "CROWDSTRIKE HOLDINGS INC - A",
            "share": 28000.0
        },
        {
            "id": "2303",
            "name": "聯電",
            "share": 4000000.0
        },
        {
            "id": "3017",
            "name": "奇鋐",
            "share": 215000.0
        },
        {
            "id": "6274",
            "name": "台燿",
            "share": 244000.0
        },
        {
            "id": "6278 JP",
            "name": "UNION TOOL CO",
            "share": 90000.0
        },
        {
            "id": "DDOG US",
            "name": "DATADOG INC - CLASS A",
            "share": 60000.0
        },
        {
            "id": "SOI FP",
            "name": "S.O.I.T.E.C.",
            "share": 90000.0
        },
        {
            "id": "AXTI US",
            "name": "AXT INC",
            "share": 140000.0
        },
        {
            "id": "603256 CH",
            "name": "GRACE FABRIC TECHNOLOGY CO-A",
            "share": 290000.0
        },
        {
            "id": "NVDA US",
            "name": "NVIDIA CORP(輝達公司)",
            "share": 37500.0
        },
        {
            "id": "7769",
            "name": "鴻勁",
            "share": 36000.0
        },
        {
            "id": "2360",
            "name": "致茂",
            "share": 100000.0
        }
    ],
    "market_prices": {
        "010120 KS": 5062.68,
        "LITE US": 26070.63,
        "268A JP": 552.24,
        "2360": 2265.0,
        "MU US": 34072.9,
        "COHR US": 12189.45,
        "VSH US": 1846.79,
        "6981 JP": 2372.83,
        "3110 JP": 4005.72,
        "6976 JP": 3399.44,
        "AVGO US": 12033.93,
        "009150 KS": 46039.39,
        "NVDA US": 6374.91,
        "2454": 4535.0,
        "WDC US": 21124.52,
        "6787 JP": 7176.59,
        "ARM US": 11683.81,
        "6920 JP": 11135.81,
        "MRVL US": 8842.2,
        "2330": 2490.0,
        "6274": 1735.0,
        "4062 JP": 5118.52,
        "AAOI US": 4816.55,
        "ENR GY": 5864.2,
        "VIAV US": 1578.14,
        "3017": 2425.0,
        "7769": 6810.0,
        "ORCL US": 5358.57,
        "2303": 170.0,
        "IFX GY": 2917.32,
        "AIXA GY": 2005.43,
        "3711": 662.0,
        "AMD US": 16412.71,
        "NBIS US": 8680.98,
        "8035 JP": 15069.86,
        "CRWD US": 21615.28,
        "DDOG US": 7012.5,
        "6223": 6680.0,
        "7826 JP": 1849.84,
        "7220 JP": 940.41,
        "6963 JP": 1100.6,
        "5801 JP": 11234.6,
        "603256 CH": 1156.28,
        "BE US": 10134.14,
        "6515": 9450.0,
        "5803 JP": 1193.39,
        "GEV US": 32982.99,
        "SNDK US": 62868.86,
        "6997 JP": 1125.4,
        "2308": 2080.0,
        "3436 JP": 817.61,
        "HOT GY": 18309.84,
        "GOOGL US": 10960.79,
        "6869 HK": 1069.12,
        "TER US": 13049.64,
        "006400 KS": 11013.91,
        "3037": 974.0,
        "GLW US": 5925.12,
        "AXTI US": 2539.27,
        "5274": 18505.0,
        "CIEN US": 14328.45,
        "SOI FP": 4317.95,
        "5706 JP": 10252.54,
        "2383": 5700.0,
        "STM US": 2281.39,
        "NOK US": 430.93,
        "6278 JP": 4699.16,
        "CRDO US": 8540.49,
        "285A JP": 21055.19,
        "FORM US": 4486.84
    }
}